sphinx_revealjs_copycode/__init__.py
sphinx_revealjs_copycode/_static/.gitignore
sphinx_revealjs_copycode-0.4.3.dist-info/METADATA
sphinx_revealjs_copycode-0.4.3.dist-info/WHEEL
sphinx_revealjs_copycode-0.4.3.dist-info/licenses/LICENSE
sphinx_revealjs_copycode-0.4.3.dist-info/RECORD
